{"id":"MLA6039","name":"Alfa Romeo","picture":null,"permalink":null,"total_items_in_this_category":216,"path_from_root":[{"id":"MLA1743","name":"Autos, Motos y Otros"},{"id":"MLA1744","name":"Autos y Camionetas"},{"id":"MLA6039","name":"Alfa Romeo"}],"children_categories":[{"id":"MLA29570","name":"145","total_items_in_this_category":27},{"id":"MLA29543","name":"146","total_items_in_this_category":16},{"id":"MLA30842","name":"147","total_items_in_this_category":4},{"id":"MLA29577","name":"155","total_items_in_this_category":9},{"id":"MLA29639","name":"156","total_items_in_this_category":12},{"id":"MLA72031","name":"156 Sportwagon","total_items_in_this_category":0},{"id":"MLA29569","name":"159","total_items_in_this_category":5},{"id":"MLA29522","name":"164","total_items_in_this_category":10},{"id":"MLA29578","name":"166","total_items_in_this_category":6},{"id":"MLA412523","name":"33","total_items_in_this_category":2},{"id":"MLA30845","name":"Brera","total_items_in_this_category":1},{"id":"MLA443919","name":"Giulia","total_items_in_this_category":0},{"id":"MLA91017","name":"Giulietta","total_items_in_this_category":44},{"id":"MLA30844","name":"GT","total_items_in_this_category":1},{"id":"MLA412524","name":"GTV","total_items_in_this_category":0},{"id":"MLA51487","name":"Mito","total_items_in_this_category":62},{"id":"MLA32343","name":"Spider","total_items_in_this_category":1},{"id":"MLA411501","name":"Zagato","total_items_in_this_category":0},{"id":"MLA29627","name":"Otros Modelos","total_items_in_this_category":5}],"attribute_types":"attributes","settings":{"adult_content":false,"buying_allowed":false,"buying_modes":["classified"],"catalog_domain":"MLA-CARS_AND_VANS","coverage_areas":"not_allowed","currencies":["USD","ARS"],"fragile":false,"immediate_payment":"optional","item_conditions":["used","not_specified","new"],"items_reviews_allowed":false,"listing_allowed":false,"max_description_length":50000,"max_pictures_per_item":15,"max_pictures_per_item_var":6,"max_sub_title_length":70,"max_title_length":60,"maximum_price":null,"minimum_price":null,"mirror_category":null,"mirror_master_category":null,"mirror_slave_categories":[],"price":"required","reservation_allowed":"mandatory","restrictions":[],"rounded_address":false,"seller_contact":"optional","shipping_modes":["not_specified","custom"],"shipping_options":[],"shipping_profile":"not_allowed","show_contact_information":true,"simple_shipping":"not_allowed","stock":"required","sub_vertical":"cars","subscribable":false,"tags":[],"vertical":"motors","vip_subdomain":"auto","buyer_protection_programs":["delivered","undelivered"],"status":"enabled"},"meta_categ_id":4869,"attributable":false,"date_created":"2018-04-25T08:12:56.000Z"}